LICENSE
MANIFEST.in
README.rst
requirements.txt
setup.py
citygml2stl/__init__.py
citygml2stl/citygml.py
citygml2stl/exceptions.py
citygml2stl/polygons.py
citygml2stl/stl.py
citygml2stl.egg-info/PKG-INFO
citygml2stl.egg-info/SOURCES.txt
citygml2stl.egg-info/dependency_links.txt
citygml2stl.egg-info/requires.txt
citygml2stl.egg-info/top_level.txt
test/__init__.py
test/test_citygml.py
test/test_polygons.py
test/test_stl.py
test/datasets/README.rst