Metadata-Version: 1.1
Name: citygml2stl
Version: 0.1.dev2
Summary: CityGML to printable STL
Home-page: UNKNOWN
Author: Miro Hrončok
Author-email: miro@hroncok.cz
License: MIT
Keywords: 3D printing,STL,mesh,CityGML
Platform: UNKNOWN
Classifier: Development Status :: 3 - Alpha
Classifier: Intended Audience :: Developers
Classifier: Intended Audience :: Manufacturing
Classifier: License :: OSI Approved :: MIT License
Classifier: Operating System :: POSIX :: Linux
Classifier: Programming Language :: Python
Classifier: Programming Language :: Python :: 2
Classifier: Programming Language :: Python :: 2.7
Classifier: Programming Language :: Python :: 3
Classifier: Programming Language :: Python :: 3.3
Classifier: Programming Language :: Python :: 3.4
